herman_code/__about__.py
herman_code/__init__.py
herman_code/classes.py
herman_code/git_commit.py
herman_code/hcode.py
herman_code/scripts.py
herman_code/code/bprint.py
herman_code/code/get_elapsed_time.py
herman_code/code/narrow_text_table.py
herman_code/code/tabulate.py
herman_code/code/utilities.py
herman_code/code/wrap.py
herman_code/templates/cli_script.py
herman_code/templates/script.py
herman_code/tests/match_test_files.py
herman_code/tests/git_commit/__init__.py
herman_code/tests/git_commit/make_solutions.py
herman_code/tests/git_commit/tests.py
herman_code/tests/git_commit/data/__init__.py
herman_code/tests/git_commit/data/negatives/01.text
herman_code/tests/git_commit/data/negatives/02.text
herman_code/tests/git_commit/data/negatives/__init__.py
herman_code/tests/git_commit/data/positives/01.text
herman_code/tests/git_commit/data/positives/02.text
herman_code/tests/git_commit/data/positives/03.text
herman_code/tests/git_commit/data/positives/04.text
herman_code/tests/git_commit/data/positives/05.text
herman_code/tests/git_commit/data/positives/06.text
herman_code/tests/git_commit/data/positives/07.text
herman_code/tests/git_commit/data/positives/08.text
herman_code/tests/git_commit/data/positives/__init__.py
herman_code/tests/git_commit/data/solutions_p/01.pickle
herman_code/tests/git_commit/data/solutions_p/02.pickle
herman_code/tests/git_commit/data/solutions_p/03.pickle
herman_code/tests/git_commit/data/solutions_p/04.pickle
herman_code/tests/git_commit/data/solutions_p/05.pickle
herman_code/tests/git_commit/data/solutions_p/06.pickle
herman_code/tests/git_commit/data/solutions_p/07.pickle
herman_code/tests/git_commit/data/solutions_p/08.pickle
herman_code/tests/git_commit/data/solutions_p/__init__.py
herman_code-0.0.5.dist-info/METADATA
herman_code-0.0.5.dist-info/WHEEL
herman_code-0.0.5.dist-info/entry_points.txt
herman_code-0.0.5.dist-info/licenses/LICENSE
herman_code-0.0.5.dist-info/RECORD
